README
setup.py
fsdbm/__init__.py
fsdbm.egg-info/PKG-INFO
fsdbm.egg-info/SOURCES.txt
fsdbm.egg-info/dependency_links.txt
fsdbm.egg-info/top_level.txt